{
  "generator-jhipster": {
    "applicationType": "monolith",
    "gitCompany": "",
    "baseName": "jhipsterSampleApplication",
    "packageName": "com.mycompany.myapp",
    "packageFolder": "com/mycompany/myapp",
    "serverPort": 8080,
    "serviceDiscoveryType": false,
    "authenticationType": "jwt",
    "cacheProvider": "ehcache",
    "enableHibernateCache": true,
    "websocket": false,
    "databaseType": "sql",
    "devDatabaseType": "h2Disk",
    "prodDatabaseType": "postgresql",
    "searchEngine": false,
    "enableSwaggerCodegen": false,
    "messageBroker": false,
    "buildTool": "maven",
    "useSass": true,
    "clientPackageManager": "npm",
    "testFrameworks": ["cucumber"],
    "enableTranslation": true,
    "nativeLanguage": "fr",
    "languages": ["fr"],
    "clientFramework": "angularX",
    "jhiPrefix": "jhi",
    "withAdminUi": true,
    "jhipsterVersion": "7.4.0",
    "skipUserManagement": false,
    "skipCheckLengthOfIdentifier": false,
    "skipFakeData": false,
    "entitySuffix": "",
    "dtoSuffix": "DTO",
    "blueprints": [],
    "otherModules": [],
    "pages": [],
    "creationTimestamp": 1640760600984,
    "jwtSecretKey": "ZDliMGI3MGNlMzhmMTUxYzI3NGIzN2MxY2YzYTRlZDVjOGQ1ZGUyZjExZGI0YjkyZTE3OGNhZmI4NmRmYTM5YjczMDA5MmMzOGI1ZTM5YjFjMmI2YzIwNWI3ZGVlN2JiMTZjM2I3MGE1NDU5ZjRmMmI2OTM4MmM2MzJhMTU4YTM=",
    "devServerPort": 4200,
    "clientTheme": "none",
    "clientThemeVariant": "",
    "reactive": false,
    "enableGradleEnterprise": false
  },
  "git-provider": "GitHub",
  "git-company": "abodje",
  "repository-name": "jhipster-sample-application"
}
